brybox/__init__.py
brybox/core/audiora/__init__.py
brybox/core/audiora/audiora.py
brybox/core/audiora/file_ops.py
brybox/core/audiora/filename.py
brybox/core/audiora/metadata.py
brybox/core/doctopus.py
brybox/core/inbox_kraken.py
brybox/core/models/__init__.py
brybox/core/models/image.py
brybox/core/pixelporter/__init__.py
brybox/core/pixelporter/deduplication.py
brybox/core/pixelporter/orchestrator.py
brybox/core/pixelporter/processing.py
brybox/core/pixelporter/protocols.py
brybox/core/pixelporter/staging.py
brybox/core/pixelporter/timestamps.py
brybox/core/porter/__init__.py
brybox/core/porter/_shared/deduplication.py
brybox/core/porter/_shared/file_filters.py
brybox/core/porter/_shared/metadata_fixers.py
brybox/core/porter/_shared/orchestration.py
brybox/core/porter/_shared/processing.py
brybox/core/porter/_shared/protocols.py
brybox/core/porter/_shared/staging.py
brybox/core/porter/models/__init__.py
brybox/core/porter/models/image.py
brybox/core/porter/motionporter/orchestrator.py
brybox/core/porter/pixelporter/orchestrator.py
brybox/core/snap_jedi/__init__.py
brybox/core/snap_jedi/converter.py
brybox/core/snap_jedi/metadata.py
brybox/core/snap_jedi/naming.py
brybox/core/snap_jedi/snapjedi.py
brybox/core/videosith/__init__.py
brybox/core/videosith/converter.py
brybox/core/videosith/metadata.py
brybox/core/videosith/metadata_writer.py
brybox/core/videosith/naming.py
brybox/core/videosith/videosith.py
brybox/events/__init__.py
brybox/events/bus.py
brybox/events/models.py
brybox/events/verifier.py
brybox/utils/__init__.py
brybox/utils/apple_files.py
brybox/utils/config_loader.py
brybox/utils/credentials.py
brybox/utils/deduplicator.py
brybox/utils/health_check.py
brybox/utils/logging.py
brybox/web_marionette/__init__.py
brybox/web_marionette/models.py
brybox/web_marionette/scrapers.py
brybox-0.5.0.dist-info/WHEEL
brybox-0.5.0.dist-info/METADATA
brybox-0.5.0.dist-info/RECORD
