Metadata-Version: 2.3
Name: brybox
Version: 0.5.0
Summary: Brybox is a personal automation toolkit for PC organization. It streamlines repetitive tasks such as PDF sorting, photo and video organization, and email/download handling. Designed to replace tedious manual workflows, Brybox provides a flexible, extensible framework for managing digital clutter with ease.
Requires-Dist: beautifulsoup4>=4.13.5
Requires-Dist: pdfplumber>=0.11.7
Requires-Dist: playwright>=1.55.0
Requires-Dist: pyexiftool>=0.5.6
Requires-Dist: python-dateutil>=2.9.0.post0
Requires-Dist: python-dotenv>=1.1.1
Requires-Dist: pytz>=2025.2
Requires-Dist: requests>=2.32.5
Requires-Dist: rich>=14.1.0
Requires-Dist: timezonefinder>=8.0.0
Requires-Python: >=3.12
